{"playerId":1642274,"player":"Yves Missi","stat":"REB","statDisplay":"REB","gameDate":"2026-03-29","recentWindow":25,"xAxis":"GAME_DATE","oppTeamIdUpcoming":"1610612752","matchupMetricCol":"OPP_POS_EST_r10","matchupMetricValue":97.62863411585882,"matchupPercentileAmongTeams":0.13333333333333333,"similarityMetricCols":["OPP_POS_EST_r10","OPP_POS_EST_r5","OPP_POS_EST_r3"],"similarityMode":"composite_zscore_quantiles","modelPred":5.924559398900562,"modelMu":5.924559398900562,"modelSigma":3.75103011412304,"expMin":19.598,"samples":{"recent":{"overall":{"n":25,"avg":6.48,"median":6.0,"std":3.4306850627826506,"max":14.0},"home":{"n":10,"avg":7.6,"median":8.0,"std":3.2310988842807027,"max":12.0},"away":{"n":15,"avg":5.733333333333333,"median":6.0,"std":3.3559234529741917,"max":14.0}},"overall":{"overall":{"n":59,"avg":5.813559322033898,"median":6.0,"std":3.290842848460035,"max":14.0},"home":{"n":29,"avg":5.793103448275862,"median":6.0,"std":3.6613480685334507,"max":14.0},"away":{"n":30,"avg":5.833333333333333,"median":6.0,"std":2.8877134360751398,"max":14.0}},"similar":{"n":10,"avg":6.1,"median":7.0,"std":3.726929030716845,"max":12.0}},"games":[{"gameId":"22500085","gameDate":"2025-10-22","seq":1,"value":7.0,"minutes":23.151666666666667,"opp":"MEM","isHome":0,"location":"Away","simBin":"Unknown","simScore":null,"simPct":null},{"gameId":"22500117","gameDate":"2025-10-27","seq":3,"value":7.0,"minutes":19.426666666666666,"opp":"BOS","isHome":1,"location":"Home","simBin":"Close 25%","simScore":0.7712593021240574,"simPct":0.27586206896551724},{"gameId":"22500134","gameDate":"2025-10-29","seq":4,"value":4.0,"minutes":23.95,"opp":"DEN","isHome":0,"location":"Away","simBin":"Far 25%","simScore":2.723919249282959,"simPct":0.9137931034482759},{"gameId":"22500027","gameDate":"2025-10-31","seq":5,"value":9.0,"minutes":27.59,"opp":"LAC","isHome":0,"location":"Away","simBin":"Closest 25%","simScore":0.22451834824073225,"simPct":0.034482758620689655},{"gameId":"22500148","gameDate":"2025-11-02","seq":6,"value":6.0,"minutes":21.95,"opp":"OKC","isHome":0,"location":"Away","simBin":"Far 25%","simScore":2.281302643413739,"simPct":0.8448275862068966},{"gameId":"22500219","gameDate":"2025-11-12","seq":11,"value":0.0,"minutes":2.05,"opp":"POR","isHome":1,"location":"Home","simBin":"Far 25%","simScore":2.7898872508069155,"simPct":0.9655172413793104},{"gameId":"22500045","gameDate":"2025-11-14","seq":12,"value":1.0,"minutes":10.3,"opp":"LAL","isHome":1,"location":"Home","simBin":"Close 25%","simScore":1.2205955122212948,"simPct":0.4827586206896552},{"gameId":"22500237","gameDate":"2025-11-16","seq":13,"value":7.0,"minutes":24.75,"opp":"GSW","isHome":1,"location":"Home","simBin":"Mid 25%","simScore":1.8338057660448213,"simPct":0.7241379310344828},{"gameId":"22500247","gameDate":"2025-11-17","seq":14,"value":2.0,"minutes":21.9,"opp":"OKC","isHome":1,"location":"Home","simBin":"Mid 25%","simScore":1.2471701321105206,"simPct":0.5172413793103449},{"gameId":"22500260","gameDate":"2025-11-19","seq":15,"value":8.0,"minutes":12.35,"opp":"DEN","isHome":1,"location":"Home","simBin":"Mid 25%","simScore":1.2888976024703778,"simPct":0.5344827586206896},{"gameId":"22500052","gameDate":"2025-11-21","seq":16,"value":2.0,"minutes":15.505,"opp":"DAL","isHome":0,"location":"Away","simBin":"Far 25%","simScore":3.714180584815038,"simPct":0.9827586206896551},{"gameId":"22500270","gameDate":"2025-11-22","seq":17,"value":3.0,"minutes":20.583333333333332,"opp":"ATL","isHome":1,"location":"Home","simBin":"Far 25%","simScore":2.0249680346075345,"simPct":0.7586206896551724},{"gameId":"22500289","gameDate":"2025-11-24","seq":18,"value":14.0,"minutes":29.251666666666665,"opp":"CHI","isHome":1,"location":"Home","simBin":"Far 25%","simScore":3.9802140981488976,"simPct":1.0},{"gameId":"22500065","gameDate":"2025-11-26","seq":19,"value":6.0,"minutes":29.403333333333332,"opp":"MEM","isHome":1,"location":"Home","simBin":"Close 25%","simScore":0.742371485547885,"simPct":0.25862068965517243},{"gameId":"22500298","gameDate":"2025-11-29","seq":20,"value":10.0,"minutes":20.306666666666665,"opp":"GSW","isHome":0,"location":"Away","simBin":"Mid 25%","simScore":1.5804057129350564,"simPct":0.6206896551724138},{"gameId":"22500308","gameDate":"2025-11-30","seq":21,"value":6.0,"minutes":23.9,"opp":"LAL","isHome":0,"location":"Away","simBin":"Close 25%","simScore":1.167732911913397,"simPct":0.4482758620689655},{"gameId":"22500350","gameDate":"2025-12-06","seq":24,"value":6.0,"minutes":17.616666666666667,"opp":"BKN","isHome":0,"location":"Away","simBin":"Closest 25%","simScore":0.6336718668769216,"simPct":0.20689655172413793},{"gameId":"22500366","gameDate":"2025-12-08","seq":25,"value":0.0,"minutes":7.64,"opp":"SAS","isHome":1,"location":"Home","simBin":"Far 25%","simScore":2.1036035276797365,"simPct":0.8103448275862069},{"gameId":"22501207","gameDate":"2025-12-11","seq":26,"value":8.0,"minutes":13.355,"opp":"POR","isHome":1,"location":"Home","simBin":"Far 25%","simScore":2.4819395265986888,"simPct":0.8793103448275862},{"gameId":"22501223","gameDate":"2025-12-14","seq":27,"value":8.0,"minutes":11.161666666666667,"opp":"CHI","isHome":0,"location":"Away","simBin":"Mid 25%","simScore":1.3478851252402961,"simPct":0.5517241379310345},{"gameId":"22500375","gameDate":"2025-12-18","seq":28,"value":2.0,"minutes":6.403333333333333,"opp":"HOU","isHome":1,"location":"Home","simBin":"Closest 25%","simScore":0.635148364677335,"simPct":0.22413793103448276},{"gameId":"22500389","gameDate":"2025-12-20","seq":29,"value":1.0,"minutes":2.9166666666666665,"opp":"IND","isHome":1,"location":"Home","simBin":"Closest 25%","simScore":0.5724457905685987,"simPct":0.1724137931034483},{"gameId":"22500412","gameDate":"2025-12-23","seq":31,"value":2.0,"minutes":12.8,"opp":"CLE","isHome":0,"location":"Away","simBin":"Far 25%","simScore":2.6957034916292373,"simPct":0.896551724137931},{"gameId":"22500429","gameDate":"2025-12-26","seq":32,"value":3.0,"minutes":18.018333333333334,"opp":"PHX","isHome":1,"location":"Home","simBin":"Close 25%","simScore":1.2104934318108522,"simPct":0.46551724137931033},{"gameId":"22500434","gameDate":"2025-12-27","seq":33,"value":8.0,"minutes":20.768333333333334,"opp":"PHX","isHome":1,"location":"Home","simBin":"Mid 25%","simScore":1.420869841740369,"simPct":0.5689655172413793},{"gameId":"22500454","gameDate":"2025-12-29","seq":34,"value":6.0,"minutes":14.351666666666667,"opp":"NYK","isHome":1,"location":"Home","simBin":"Mid 25%","simScore":1.467049539790312,"simPct":0.5862068965517241},{"gameId":"22500466","gameDate":"2025-12-31","seq":35,"value":6.0,"minutes":22.688333333333333,"opp":"CHI","isHome":0,"location":"Away","simBin":"Mid 25%","simScore":1.7236540160021334,"simPct":0.7068965517241379},{"gameId":"22500482","gameDate":"2026-01-02","seq":36,"value":3.0,"minutes":20.95,"opp":"POR","isHome":1,"location":"Home","simBin":"Far 25%","simScore":2.277887943480463,"simPct":0.8275862068965517},{"gameId":"22500497","gameDate":"2026-01-04","seq":37,"value":5.0,"minutes":17.066666666666666,"opp":"MIA","isHome":0,"location":"Away","simBin":"Far 25%","simScore":2.086012137656694,"simPct":0.7931034482758621},{"gameId":"22500514","gameDate":"2026-01-06","seq":38,"value":6.0,"minutes":15.681666666666667,"opp":"LAL","isHome":1,"location":"Home","simBin":"Mid 25%","simScore":1.665552435339021,"simPct":0.6896551724137931},{"gameId":"22500519","gameDate":"2026-01-07","seq":39,"value":4.0,"minutes":24.416666666666668,"opp":"ATL","isHome":0,"location":"Away","simBin":"Far 25%","simScore":2.740632117177291,"simPct":0.9310344827586207},{"gameId":"22500534","gameDate":"2026-01-09","seq":40,"value":9.0,"minutes":12.693333333333333,"opp":"WAS","isHome":0,"location":"Away","simBin":"Far 25%","simScore":2.378514087006168,"simPct":0.8620689655172413},{"gameId":"22500548","gameDate":"2026-01-11","seq":41,"value":5.0,"minutes":18.098333333333333,"opp":"ORL","isHome":0,"location":"Away","simBin":"Close 25%","simScore":1.035815568359444,"simPct":0.3793103448275862},{"gameId":"22500567","gameDate":"2026-01-13","seq":42,"value":7.0,"minutes":19.22,"opp":"DEN","isHome":1,"location":"Home","simBin":"Closest 25%","simScore":0.5709069059897462,"simPct":0.15517241379310345},{"gameId":"22500574","gameDate":"2026-01-14","seq":43,"value":12.0,"minutes":34.11,"opp":"BKN","isHome":1,"location":"Home","simBin":"Closest 25%","simScore":0.34702556570842447,"simPct":0.10344827586206896},{"gameId":"22500588","gameDate":"2026-01-16","seq":44,"value":3.0,"minutes":19.903333333333332,"opp":"IND","isHome":0,"location":"Away","simBin":"Mid 25%","simScore":1.8822156569494473,"simPct":0.7413793103448276},{"gameId":"22500604","gameDate":"2026-01-18","seq":45,"value":6.0,"minutes":30.445,"opp":"HOU","isHome":0,"location":"Away","simBin":"Closest 25%","simScore":0.26646790141053445,"simPct":0.05172413793103448},{"gameId":"22500624","gameDate":"2026-01-21","seq":46,"value":6.0,"minutes":26.366666666666667,"opp":"DET","isHome":1,"location":"Home","simBin":"Close 25%","simScore":0.9650627718310085,"simPct":0.3275862068965517},{"gameId":"22500639","gameDate":"2026-01-23","seq":47,"value":8.0,"minutes":21.316666666666666,"opp":"MEM","isHome":0,"location":"Away","simBin":"Far 25%","simScore":2.0472688375219,"simPct":0.7758620689655172},{"gameId":"22500654","gameDate":"2026-01-25","seq":48,"value":14.0,"minutes":30.286666666666665,"opp":"SAS","isHome":0,"location":"Away","simBin":"Close 25%","simScore":1.1529359426968853,"simPct":0.43103448275862066},{"gameId":"22500667","gameDate":"2026-01-27","seq":49,"value":6.0,"minutes":21.225,"opp":"OKC","isHome":0,"location":"Away","simBin":"Close 25%","simScore":1.224543912475586,"simPct":0.5},{"gameId":"22500691","gameDate":"2026-01-30","seq":50,"value":4.0,"minutes":14.116666666666667,"opp":"MEM","isHome":1,"location":"Home","simBin":"Mid 25%","simScore":1.6626397954497083,"simPct":0.6724137931034483},{"gameId":"22500699","gameDate":"2026-01-31","seq":51,"value":8.0,"minutes":27.983333333333334,"opp":"PHI","isHome":0,"location":"Away","simBin":"Close 25%","simScore":1.0976875080330475,"simPct":0.41379310344827586},{"gameId":"22500712","gameDate":"2026-02-02","seq":52,"value":1.0,"minutes":10.633333333333333,"opp":"CHA","isHome":0,"location":"Away","simBin":"Closest 25%","simScore":0.2234702223853203,"simPct":0.017241379310344827},{"gameId":"22500729","gameDate":"2026-02-04","seq":53,"value":7.0,"minutes":30.818333333333335,"opp":"MIL","isHome":0,"location":"Away","simBin":"Closest 25%","simScore":0.32408377028348095,"simPct":0.06896551724137931},{"gameId":"22500744","gameDate":"2026-02-06","seq":54,"value":4.0,"minutes":15.366666666666667,"opp":"MIN","isHome":0,"location":"Away","simBin":"Mid 25%","simScore":1.6320481414212136,"simPct":0.6379310344827587},{"gameId":"22500766","gameDate":"2026-02-09","seq":55,"value":5.0,"minutes":21.816666666666666,"opp":"SAC","isHome":1,"location":"Home","simBin":"Close 25%","simScore":0.8333567918255932,"simPct":0.3103448275862069},{"gameId":"22500867","gameDate":"2026-02-28","seq":61,"value":3.0,"minutes":11.616666666666667,"opp":"UTA","isHome":0,"location":"Away","simBin":"Far 25%","simScore":2.7517052727598,"simPct":0.9482758620689655},{"gameId":"22500877","gameDate":"2026-03-01","seq":62,"value":8.0,"minutes":20.393333333333334,"opp":"LAC","isHome":0,"location":"Away","simBin":"Close 25%","simScore":0.8018964529816816,"simPct":0.29310344827586204},{"gameId":"22500891","gameDate":"2026-03-03","seq":63,"value":1.0,"minutes":5.983333333333333,"opp":"LAL","isHome":0,"location":"Away","simBin":"Closest 25%","simScore":0.340732446220191,"simPct":0.08620689655172414},{"gameId":"22500907","gameDate":"2026-03-05","seq":64,"value":2.0,"minutes":15.733333333333333,"opp":"SAC","isHome":0,"location":"Away","simBin":"Mid 25%","simScore":1.653704517217589,"simPct":0.6551724137931034},{"gameId":"22500912","gameDate":"2026-03-06","seq":65,"value":8.0,"minutes":16.423333333333332,"opp":"PHX","isHome":0,"location":"Away","simBin":"Closest 25%","simScore":0.6178968269414543,"simPct":0.1896551724137931},{"gameId":"22500925","gameDate":"2026-03-08","seq":66,"value":2.0,"minutes":14.75,"opp":"WAS","isHome":1,"location":"Home","simBin":"Close 25%","simScore":1.0120152098923956,"simPct":0.3620689655172414},{"gameId":"22500948","gameDate":"2026-03-11","seq":67,"value":10.0,"minutes":19.283333333333335,"opp":"TOR","isHome":1,"location":"Home","simBin":"Closest 25%","simScore":0.46347254939824484,"simPct":0.1206896551724138},{"gameId":"22500964","gameDate":"2026-03-13","seq":68,"value":7.0,"minutes":25.386666666666667,"opp":"HOU","isHome":0,"location":"Away","simBin":"Closest 25%","simScore":0.5653722823038495,"simPct":0.13793103448275862},{"gameId":"22500988","gameDate":"2026-03-16","seq":69,"value":10.0,"minutes":28.166666666666668,"opp":"DAL","isHome":1,"location":"Home","simBin":"Mid 25%","simScore":1.5387217818381496,"simPct":0.603448275862069},{"gameId":"22501005","gameDate":"2026-03-18","seq":70,"value":6.0,"minutes":18.75,"opp":"LAC","isHome":1,"location":"Home","simBin":"Close 25%","simScore":1.0409409739591162,"simPct":0.39655172413793105},{"gameId":"22501012","gameDate":"2026-03-19","seq":71,"value":11.0,"minutes":27.32,"opp":"LAC","isHome":1,"location":"Home","simBin":"Closest 25%","simScore":0.7278445839023083,"simPct":0.2413793103448276},{"gameId":"22501025","gameDate":"2026-03-21","seq":72,"value":10.0,"minutes":24.183333333333334,"opp":"CLE","isHome":1,"location":"Home","simBin":"Close 25%","simScore":0.9808089080085437,"simPct":0.3448275862068966}],"similarGames":[{"gameId":"22500027","gameDate":"2025-10-31","seq":5,"value":9.0,"minutes":27.59,"opp":"LAC","isHome":0,"location":"Away","simBin":"Closest 25%","simScore":0.22451834824073225,"simPct":0.034482758620689655},{"gameId":"22500389","gameDate":"2025-12-20","seq":29,"value":1.0,"minutes":2.9166666666666665,"opp":"IND","isHome":1,"location":"Home","simBin":"Closest 25%","simScore":0.5724457905685987,"simPct":0.1724137931034483},{"gameId":"22500567","gameDate":"2026-01-13","seq":42,"value":7.0,"minutes":19.22,"opp":"DEN","isHome":1,"location":"Home","simBin":"Closest 25%","simScore":0.5709069059897462,"simPct":0.15517241379310345},{"gameId":"22500574","gameDate":"2026-01-14","seq":43,"value":12.0,"minutes":34.11,"opp":"BKN","isHome":1,"location":"Home","simBin":"Closest 25%","simScore":0.34702556570842447,"simPct":0.10344827586206896},{"gameId":"22500604","gameDate":"2026-01-18","seq":45,"value":6.0,"minutes":30.445,"opp":"HOU","isHome":0,"location":"Away","simBin":"Closest 25%","simScore":0.26646790141053445,"simPct":0.05172413793103448},{"gameId":"22500712","gameDate":"2026-02-02","seq":52,"value":1.0,"minutes":10.633333333333333,"opp":"CHA","isHome":0,"location":"Away","simBin":"Closest 25%","simScore":0.2234702223853203,"simPct":0.017241379310344827},{"gameId":"22500729","gameDate":"2026-02-04","seq":53,"value":7.0,"minutes":30.818333333333335,"opp":"MIL","isHome":0,"location":"Away","simBin":"Closest 25%","simScore":0.32408377028348095,"simPct":0.06896551724137931},{"gameId":"22500891","gameDate":"2026-03-03","seq":63,"value":1.0,"minutes":5.983333333333333,"opp":"LAL","isHome":0,"location":"Away","simBin":"Closest 25%","simScore":0.340732446220191,"simPct":0.08620689655172414},{"gameId":"22500948","gameDate":"2026-03-11","seq":67,"value":10.0,"minutes":19.283333333333335,"opp":"TOR","isHome":1,"location":"Home","simBin":"Closest 25%","simScore":0.46347254939824484,"simPct":0.1206896551724138},{"gameId":"22500964","gameDate":"2026-03-13","seq":68,"value":7.0,"minutes":25.386666666666667,"opp":"HOU","isHome":0,"location":"Away","simBin":"Closest 25%","simScore":0.5653722823038495,"simPct":0.13793103448275862}],"team":"","opp":"","location":"Home","matchup":""}