{"playerId":1641739,"player":"Toumani Camara","stat":"PTS","statDisplay":"PTS","gameDate":"2026-04-02","recentWindow":25,"xAxis":"GAME_DATE","oppTeamIdUpcoming":"1610612746","matchupMetricCol":"OPP_PTS_ALLOWED_r10","matchupMetricValue":113.6,"matchupPercentileAmongTeams":0.4,"similarityMetricCols":["OPP_PTS_ALLOWED_r10","OPP_PTS_ALLOWED_r5","OPP_PTS_ALLOWED_r3"],"similarityMode":"composite_zscore_quantiles","modelPred":12.9052433269129,"modelMu":12.9052433269129,"modelSigma":6.060892212736868,"expMin":30.77090337155532,"samples":{"recent":{"overall":{"n":25,"avg":13.48,"median":12.0,"std":7.04908504701142,"max":35.0},"home":{"n":12,"avg":14.666666666666666,"median":11.0,"std":9.177266598624136,"max":35.0},"away":{"n":13,"avg":12.384615384615385,"median":12.0,"std":3.9132607206082786,"max":18.0}},"overall":{"overall":{"n":75,"avg":13.093333333333334,"median":13.0,"std":6.020350672695256,"max":35.0},"home":{"n":37,"avg":14.0,"median":13.0,"std":6.472394602609755,"max":35.0},"away":{"n":38,"avg":12.210526315789474,"median":13.0,"std":5.40057450519383,"max":21.0}},"similar":{"n":10,"avg":15.9,"median":14.0,"std":7.258787777583803,"max":30.0}},"games":[{"gameId":"22500089","gameDate":"2025-10-22","seq":1,"value":10.0,"minutes":34.733333333333334,"opp":"MIN","isHome":1,"location":"Home","simBin":"Unknown","simScore":null,"simPct":null},{"gameId":"22500097","gameDate":"2025-10-24","seq":2,"value":19.0,"minutes":32.733333333333334,"opp":"GSW","isHome":1,"location":"Home","simBin":"Far 25%","simScore":1.6237055135972136,"simPct":0.7702702702702703},{"gameId":"22500112","gameDate":"2025-10-26","seq":3,"value":5.0,"minutes":33.0,"opp":"LAC","isHome":0,"location":"Away","simBin":"Close 25%","simScore":1.0064471416389675,"simPct":0.40540540540540543},{"gameId":"22500122","gameDate":"2025-10-27","seq":4,"value":4.0,"minutes":30.283333333333335,"opp":"LAL","isHome":0,"location":"Away","simBin":"Mid 25%","simScore":1.1207542475571606,"simPct":0.5135135135135135},{"gameId":"22500135","gameDate":"2025-10-29","seq":5,"value":17.0,"minutes":31.416666666666668,"opp":"UTA","isHome":0,"location":"Away","simBin":"Close 25%","simScore":1.0293085628226069,"simPct":0.4594594594594595},{"gameId":"22500026","gameDate":"2025-10-31","seq":6,"value":14.0,"minutes":30.436666666666667,"opp":"DEN","isHome":1,"location":"Home","simBin":"Closest 25%","simScore":0.3948688834664398,"simPct":0.08108108108108109},{"gameId":"22500163","gameDate":"2025-11-03","seq":7,"value":14.0,"minutes":34.25,"opp":"LAL","isHome":1,"location":"Home","simBin":"Mid 25%","simScore":1.186934990349186,"simPct":0.5405405405405406},{"gameId":"22500180","gameDate":"2025-11-05","seq":8,"value":16.0,"minutes":37.251666666666665,"opp":"OKC","isHome":1,"location":"Home","simBin":"Closest 25%","simScore":0.665390225003678,"simPct":0.20270270270270271},{"gameId":"22500187","gameDate":"2025-11-08","seq":9,"value":13.0,"minutes":39.21666666666667,"opp":"MIA","isHome":0,"location":"Away","simBin":"Mid 25%","simScore":1.1705381521913862,"simPct":0.527027027027027},{"gameId":"22500200","gameDate":"2025-11-10","seq":10,"value":8.0,"minutes":33.85,"opp":"ORL","isHome":0,"location":"Away","simBin":"Close 25%","simScore":0.8164606505337556,"simPct":0.32432432432432434},{"gameId":"22500219","gameDate":"2025-11-12","seq":11,"value":13.0,"minutes":38.43333333333333,"opp":"NOP","isHome":0,"location":"Away","simBin":"Mid 25%","simScore":1.468251164005007,"simPct":0.7432432432432432},{"gameId":"22500042","gameDate":"2025-11-14","seq":12,"value":16.0,"minutes":33.4,"opp":"HOU","isHome":0,"location":"Away","simBin":"Close 25%","simScore":0.7943492673506464,"simPct":0.3108108108108108},{"gameId":"22500238","gameDate":"2025-11-16","seq":13,"value":11.0,"minutes":40.516666666666666,"opp":"DAL","isHome":0,"location":"Away","simBin":"Mid 25%","simScore":1.398964105568777,"simPct":0.7027027027027027},{"gameId":"22500254","gameDate":"2025-11-18","seq":14,"value":6.0,"minutes":32.25,"opp":"PHX","isHome":1,"location":"Home","simBin":"Close 25%","simScore":0.7264750120502786,"simPct":0.25675675675675674},{"gameId":"22500263","gameDate":"2025-11-19","seq":15,"value":14.0,"minutes":37.29333333333334,"opp":"CHI","isHome":1,"location":"Home","simBin":"Far 25%","simScore":2.882830190096405,"simPct":0.9864864864864865},{"gameId":"22500056","gameDate":"2025-11-21","seq":16,"value":20.0,"minutes":33.931666666666665,"opp":"GSW","isHome":0,"location":"Away","simBin":"Closest 25%","simScore":0.697373406445655,"simPct":0.22972972972972974},{"gameId":"22500280","gameDate":"2025-11-23","seq":17,"value":4.0,"minutes":26.566666666666666,"opp":"OKC","isHome":0,"location":"Away","simBin":"Close 25%","simScore":1.0203636059824197,"simPct":0.43243243243243246},{"gameId":"22500288","gameDate":"2025-11-24","seq":18,"value":13.0,"minutes":31.516666666666666,"opp":"MIL","isHome":0,"location":"Away","simBin":"Far 25%","simScore":1.9978722300545577,"simPct":0.8513513513513513},{"gameId":"22500067","gameDate":"2025-11-26","seq":19,"value":10.0,"minutes":30.301666666666666,"opp":"SAS","isHome":1,"location":"Home","simBin":"Closest 25%","simScore":0.6681530844801628,"simPct":0.21621621621621623},{"gameId":"22500305","gameDate":"2025-11-30","seq":20,"value":19.0,"minutes":37.93333333333333,"opp":"OKC","isHome":1,"location":"Home","simBin":"Close 25%","simScore":0.870581045604414,"simPct":0.35135135135135137},{"gameId":"22500319","gameDate":"2025-12-02","seq":21,"value":21.0,"minutes":35.751666666666665,"opp":"TOR","isHome":0,"location":"Away","simBin":"Closest 25%","simScore":0.6023304861429284,"simPct":0.17567567567567569},{"gameId":"22500324","gameDate":"2025-12-03","seq":22,"value":17.0,"minutes":35.093333333333334,"opp":"CLE","isHome":0,"location":"Away","simBin":"Mid 25%","simScore":1.1879909450589834,"simPct":0.5540540540540541},{"gameId":"22500342","gameDate":"2025-12-05","seq":23,"value":1.0,"minutes":24.366666666666667,"opp":"DET","isHome":0,"location":"Away","simBin":"Close 25%","simScore":0.8800495814919462,"simPct":0.3783783783783784},{"gameId":"22500360","gameDate":"2025-12-07","seq":24,"value":13.0,"minutes":32.733333333333334,"opp":"MEM","isHome":0,"location":"Away","simBin":"Close 25%","simScore":0.785801147727025,"simPct":0.2972972972972973},{"gameId":"22501207","gameDate":"2025-12-11","seq":25,"value":15.0,"minutes":27.816666666666666,"opp":"NOP","isHome":0,"location":"Away","simBin":"Far 25%","simScore":2.7347050789412344,"simPct":0.9459459459459459},{"gameId":"22501221","gameDate":"2025-12-14","seq":26,"value":7.0,"minutes":25.455,"opp":"GSW","isHome":1,"location":"Home","simBin":"Closest 25%","simScore":0.4085684325966022,"simPct":0.0945945945945946},{"gameId":"22500380","gameDate":"2025-12-18","seq":27,"value":17.0,"minutes":34.62,"opp":"SAC","isHome":1,"location":"Home","simBin":"Far 25%","simScore":1.7008874505408589,"simPct":0.7837837837837838},{"gameId":"22500394","gameDate":"2025-12-20","seq":28,"value":15.0,"minutes":36.52,"opp":"SAC","isHome":0,"location":"Away","simBin":"Far 25%","simScore":2.1089774390719302,"simPct":0.8783783783783784},{"gameId":"22500408","gameDate":"2025-12-22","seq":29,"value":8.0,"minutes":29.378333333333334,"opp":"DET","isHome":1,"location":"Home","simBin":"Closest 25%","simScore":0.24836518580967204,"simPct":0.04054054054054054},{"gameId":"22500420","gameDate":"2025-12-23","seq":30,"value":10.0,"minutes":39.623333333333335,"opp":"ORL","isHome":1,"location":"Home","simBin":"Far 25%","simScore":1.7266011745239709,"simPct":0.7972972972972973},{"gameId":"22500431","gameDate":"2025-12-26","seq":31,"value":20.0,"minutes":39.19166666666667,"opp":"LAC","isHome":1,"location":"Home","simBin":"Closest 25%","simScore":0.43535731658913357,"simPct":0.10810810810810811},{"gameId":"22500444","gameDate":"2025-12-28","seq":32,"value":20.0,"minutes":35.07,"opp":"BOS","isHome":1,"location":"Home","simBin":"Closest 25%","simScore":0.3824370828474332,"simPct":0.06756756756756757},{"gameId":"22500457","gameDate":"2025-12-29","seq":33,"value":9.0,"minutes":25.453333333333333,"opp":"DAL","isHome":1,"location":"Home","simBin":"Far 25%","simScore":1.9012757056768816,"simPct":0.8243243243243243},{"gameId":"22500470","gameDate":"2025-12-31","seq":34,"value":6.0,"minutes":33.5,"opp":"OKC","isHome":0,"location":"Away","simBin":"Mid 25%","simScore":1.2090122970196893,"simPct":0.5675675675675675},{"gameId":"22500482","gameDate":"2026-01-02","seq":35,"value":14.0,"minutes":33.733333333333334,"opp":"NOP","isHome":0,"location":"Away","simBin":"Far 25%","simScore":2.4428456129114955,"simPct":0.9324324324324325},{"gameId":"22500490","gameDate":"2026-01-03","seq":36,"value":20.0,"minutes":35.78333333333333,"opp":"SAS","isHome":0,"location":"Away","simBin":"Mid 25%","simScore":1.2719509070997548,"simPct":0.6351351351351351},{"gameId":"22500509","gameDate":"2026-01-05","seq":37,"value":15.0,"minutes":35.278333333333336,"opp":"UTA","isHome":1,"location":"Home","simBin":"Far 25%","simScore":2.3525515898034937,"simPct":0.9054054054054054},{"gameId":"22500527","gameDate":"2026-01-07","seq":38,"value":14.0,"minutes":38.751666666666665,"opp":"HOU","isHome":1,"location":"Home","simBin":"Closest 25%","simScore":0.3167863613227931,"simPct":0.05405405405405406},{"gameId":"22500540","gameDate":"2026-01-09","seq":39,"value":25.0,"minutes":39.623333333333335,"opp":"HOU","isHome":1,"location":"Home","simBin":"Closest 25%","simScore":0.5456991149422058,"simPct":0.13513513513513514},{"gameId":"22500551","gameDate":"2026-01-11","seq":40,"value":11.0,"minutes":38.86,"opp":"NYK","isHome":1,"location":"Home","simBin":"Mid 25%","simScore":1.3279405042351262,"simPct":0.6486486486486487},{"gameId":"22500570","gameDate":"2026-01-13","seq":41,"value":6.0,"minutes":28.733333333333334,"opp":"GSW","isHome":0,"location":"Away","simBin":"Close 25%","simScore":0.8632867316855292,"simPct":0.33783783783783783},{"gameId":"22500585","gameDate":"2026-01-15","seq":42,"value":11.0,"minutes":38.13333333333333,"opp":"ATL","isHome":1,"location":"Home","simBin":"Close 25%","simScore":0.7575420070197518,"simPct":0.2702702702702703},{"gameId":"22500601","gameDate":"2026-01-17","seq":43,"value":9.0,"minutes":26.416666666666668,"opp":"LAL","isHome":1,"location":"Home","simBin":"Mid 25%","simScore":1.4558387499673968,"simPct":0.7297297297297297},{"gameId":"22500606","gameDate":"2026-01-18","seq":44,"value":17.0,"minutes":36.4,"opp":"SAC","isHome":0,"location":"Away","simBin":"Closest 25%","simScore":0.6551142120726966,"simPct":0.1891891891891892},{"gameId":"22500634","gameDate":"2026-01-22","seq":45,"value":16.0,"minutes":35.37,"opp":"MIA","isHome":1,"location":"Home","simBin":"Far 25%","simScore":1.9501836307002698,"simPct":0.8378378378378378},{"gameId":"22500642","gameDate":"2026-01-23","seq":46,"value":16.0,"minutes":37.07666666666667,"opp":"TOR","isHome":1,"location":"Home","simBin":"Close 25%","simScore":0.9064314178042464,"simPct":0.3918918918918919},{"gameId":"22500660","gameDate":"2026-01-26","seq":47,"value":18.0,"minutes":36.21666666666667,"opp":"BOS","isHome":0,"location":"Away","simBin":"Close 25%","simScore":0.8785520581068011,"simPct":0.36486486486486486},{"gameId":"22500664","gameDate":"2026-01-27","seq":48,"value":16.0,"minutes":32.86666666666667,"opp":"WAS","isHome":0,"location":"Away","simBin":"Close 25%","simScore":1.1089551217461238,"simPct":0.5},{"gameId":"22500690","gameDate":"2026-01-30","seq":49,"value":0.0,"minutes":26.433333333333334,"opp":"NYK","isHome":0,"location":"Away","simBin":"Mid 25%","simScore":1.347401038755647,"simPct":0.6621621621621622},{"gameId":"22500710","gameDate":"2026-02-01","seq":50,"value":12.0,"minutes":29.633333333333333,"opp":"CLE","isHome":1,"location":"Home","simBin":"Closest 25%","simScore":0.44202857630029485,"simPct":0.12162162162162163},{"gameId":"22500725","gameDate":"2026-02-03","seq":51,"value":13.0,"minutes":38.085,"opp":"PHX","isHome":1,"location":"Home","simBin":"Closest 25%","simScore":0.5893749610956694,"simPct":0.14864864864864866},{"gameId":"22500745","gameDate":"2026-02-06","seq":52,"value":15.0,"minutes":29.55,"opp":"MEM","isHome":1,"location":"Home","simBin":"Far 25%","simScore":2.03502098215654,"simPct":0.8648648648648649},{"gameId":"22500755","gameDate":"2026-02-07","seq":53,"value":8.0,"minutes":33.8,"opp":"MEM","isHome":1,"location":"Home","simBin":"Far 25%","simScore":2.379884029288186,"simPct":0.918918918918919},{"gameId":"22500770","gameDate":"2026-02-09","seq":54,"value":30.0,"minutes":27.49,"opp":"PHI","isHome":1,"location":"Home","simBin":"Closest 25%","simScore":0.22638265259074744,"simPct":0.02702702702702703},{"gameId":"22500783","gameDate":"2026-02-11","seq":55,"value":9.0,"minutes":32.083333333333336,"opp":"MIN","isHome":0,"location":"Away","simBin":"Mid 25%","simScore":1.262620696395745,"simPct":0.6081081081081081},{"gameId":"22500790","gameDate":"2026-02-12","seq":56,"value":14.0,"minutes":29.04,"opp":"UTA","isHome":0,"location":"Away","simBin":"Close 25%","simScore":0.7848399664688076,"simPct":0.28378378378378377},{"gameId":"22500810","gameDate":"2026-02-20","seq":57,"value":10.0,"minutes":26.35,"opp":"DEN","isHome":1,"location":"Home","simBin":"Mid 25%","simScore":1.3642999518914838,"simPct":0.6756756756756757},{"gameId":"22500826","gameDate":"2026-02-22","seq":58,"value":12.0,"minutes":34.81666666666667,"opp":"PHX","isHome":0,"location":"Away","simBin":"Mid 25%","simScore":1.2695649717307707,"simPct":0.6216216216216216},{"gameId":"22500841","gameDate":"2026-02-24","seq":59,"value":11.0,"minutes":37.465,"opp":"MIN","isHome":1,"location":"Home","simBin":"Mid 25%","simScore":1.3985345288278161,"simPct":0.6891891891891891},{"gameId":"22500853","gameDate":"2026-02-26","seq":60,"value":16.0,"minutes":36.416666666666664,"opp":"CHI","isHome":0,"location":"Away","simBin":"Far 25%","simScore":1.8494914502440742,"simPct":0.8108108108108109},{"gameId":"22500863","gameDate":"2026-02-28","seq":61,"value":12.0,"minutes":32.495,"opp":"CHA","isHome":0,"location":"Away","simBin":"Closest 25%","simScore":0.6002941448752915,"simPct":0.16216216216216217},{"gameId":"22500873","gameDate":"2026-03-01","seq":62,"value":9.0,"minutes":34.733333333333334,"opp":"ATL","isHome":0,"location":"Away","simBin":"Closest 25%","simScore":0.1447252785587549,"simPct":0.013513513513513514},{"gameId":"22500896","gameDate":"2026-03-04","seq":63,"value":9.0,"minutes":39.67666666666667,"opp":"MEM","isHome":0,"location":"Away","simBin":"Close 25%","simScore":1.0230272945849377,"simPct":0.44594594594594594},{"gameId":"22500910","gameDate":"2026-03-06","seq":64,"value":16.0,"minutes":39.46666666666667,"opp":"HOU","isHome":0,"location":"Away","simBin":"Close 25%","simScore":1.085664733405711,"simPct":0.4864864864864865},{"gameId":"22500929","gameDate":"2026-03-08","seq":65,"value":7.0,"minutes":28.316666666666666,"opp":"IND","isHome":1,"location":"Home","simBin":"Far 25%","simScore":2.759996439548621,"simPct":0.972972972972973},{"gameId":"22500944","gameDate":"2026-03-10","seq":66,"value":11.0,"minutes":35.865,"opp":"CHA","isHome":1,"location":"Home","simBin":"Close 25%","simScore":1.0170011736597189,"simPct":0.4189189189189189},{"gameId":"22500967","gameDate":"2026-03-13","seq":67,"value":5.0,"minutes":22.801666666666666,"opp":"UTA","isHome":1,"location":"Home","simBin":"Far 25%","simScore":1.5031811199409297,"simPct":0.7567567567567568},{"gameId":"22500980","gameDate":"2026-03-15","seq":68,"value":7.0,"minutes":31.086666666666666,"opp":"PHI","isHome":0,"location":"Away","simBin":"Mid 25%","simScore":1.4221434353960696,"simPct":0.7162162162162162},{"gameId":"22500985","gameDate":"2026-03-16","seq":69,"value":18.0,"minutes":31.683333333333334,"opp":"BKN","isHome":0,"location":"Away","simBin":"Mid 25%","simScore":1.2323051611156686,"simPct":0.581081081081081},{"gameId":"22501001","gameDate":"2026-03-18","seq":70,"value":17.0,"minutes":30.016666666666666,"opp":"IND","isHome":0,"location":"Away","simBin":"Far 25%","simScore":2.136784029494998,"simPct":0.8918918918918919},{"gameId":"22501020","gameDate":"2026-03-20","seq":71,"value":6.0,"minutes":34.0,"opp":"MIN","isHome":0,"location":"Away","simBin":"Close 25%","simScore":1.0627870193202245,"simPct":0.47297297297297297},{"gameId":"22501032","gameDate":"2026-03-22","seq":72,"value":16.0,"minutes":30.233333333333334,"opp":"DEN","isHome":0,"location":"Away","simBin":"Mid 25%","simScore":1.2362570960170196,"simPct":0.5945945945945946},{"gameId":"22501045","gameDate":"2026-03-23","seq":73,"value":35.0,"minutes":28.24,"opp":"BKN","isHome":1,"location":"Home","simBin":"Closest 25%","simScore":0.724777242315649,"simPct":0.24324324324324326},{"gameId":"22501074","gameDate":"2026-03-27","seq":74,"value":8.0,"minutes":38.65,"opp":"DAL","isHome":1,"location":"Home","simBin":"Far 25%","simScore":3.6011794458987887,"simPct":1.0},{"gameId":"22501087","gameDate":"2026-03-29","seq":75,"value":23.0,"minutes":28.233333333333334,"opp":"WAS","isHome":1,"location":"Home","simBin":"Far 25%","simScore":2.741877311778659,"simPct":0.9594594594594594}],"similarGames":[{"gameId":"22500026","gameDate":"2025-10-31","seq":6,"value":14.0,"minutes":30.436666666666667,"opp":"DEN","isHome":1,"location":"Home","simBin":"Closest 25%","simScore":0.3948688834664398,"simPct":0.08108108108108109},{"gameId":"22501221","gameDate":"2025-12-14","seq":26,"value":7.0,"minutes":25.455,"opp":"GSW","isHome":1,"location":"Home","simBin":"Closest 25%","simScore":0.4085684325966022,"simPct":0.0945945945945946},{"gameId":"22500408","gameDate":"2025-12-22","seq":29,"value":8.0,"minutes":29.378333333333334,"opp":"DET","isHome":1,"location":"Home","simBin":"Closest 25%","simScore":0.24836518580967204,"simPct":0.04054054054054054},{"gameId":"22500431","gameDate":"2025-12-26","seq":31,"value":20.0,"minutes":39.19166666666667,"opp":"LAC","isHome":1,"location":"Home","simBin":"Closest 25%","simScore":0.43535731658913357,"simPct":0.10810810810810811},{"gameId":"22500444","gameDate":"2025-12-28","seq":32,"value":20.0,"minutes":35.07,"opp":"BOS","isHome":1,"location":"Home","simBin":"Closest 25%","simScore":0.3824370828474332,"simPct":0.06756756756756757},{"gameId":"22500527","gameDate":"2026-01-07","seq":38,"value":14.0,"minutes":38.751666666666665,"opp":"HOU","isHome":1,"location":"Home","simBin":"Closest 25%","simScore":0.3167863613227931,"simPct":0.05405405405405406},{"gameId":"22500540","gameDate":"2026-01-09","seq":39,"value":25.0,"minutes":39.623333333333335,"opp":"HOU","isHome":1,"location":"Home","simBin":"Closest 25%","simScore":0.5456991149422058,"simPct":0.13513513513513514},{"gameId":"22500710","gameDate":"2026-02-01","seq":50,"value":12.0,"minutes":29.633333333333333,"opp":"CLE","isHome":1,"location":"Home","simBin":"Closest 25%","simScore":0.44202857630029485,"simPct":0.12162162162162163},{"gameId":"22500770","gameDate":"2026-02-09","seq":54,"value":30.0,"minutes":27.49,"opp":"PHI","isHome":1,"location":"Home","simBin":"Closest 25%","simScore":0.22638265259074744,"simPct":0.02702702702702703},{"gameId":"22500873","gameDate":"2026-03-01","seq":62,"value":9.0,"minutes":34.733333333333334,"opp":"ATL","isHome":0,"location":"Away","simBin":"Closest 25%","simScore":0.1447252785587549,"simPct":0.013513513513513514}],"team":"","opp":"","location":"Home","matchup":""}