{"playerId":1641727,"player":"Dariq Whitehead","stat":"TPM","statDisplay":"TPM","gameDate":"2026-04-08","recentWindow":25,"xAxis":"GAME_DATE","oppTeamIdUpcoming":"1610612739","matchupMetricCol":"OPP_DRtg_r10","matchupMetricValue":118.72240548702348,"matchupPercentileAmongTeams":0.6666666666666666,"similarityMetricCols":[],"similarityMode":"single_metric_absdiff","modelPred":1.951623056837244,"modelMu":1.951623056837244,"modelSigma":1.3622976183679625,"expMin":30.70572795554957,"samples":{"recent":{"overall":{"n":2,"avg":2.0,"median":2.0,"std":1.0,"max":3.0},"home":{"n":1,"avg":1.0,"median":1.0,"std":0.0,"max":1.0},"away":{"n":1,"avg":3.0,"median":3.0,"std":0.0,"max":3.0}},"overall":{"overall":{"n":2,"avg":2.0,"median":2.0,"std":1.0,"max":3.0},"home":{"n":1,"avg":1.0,"median":1.0,"std":0.0,"max":1.0},"away":{"n":1,"avg":3.0,"median":3.0,"std":0.0,"max":3.0}},"similar":{"n":2,"avg":2.0,"median":2.0,"std":1.0,"max":3.0}},"games":[{"gameId":"22501125","gameDate":"2026-04-03","seq":1,"value":1.0,"minutes":22.283333333333335,"opp":"TOR","isHome":1,"location":"Home","simBin":"3\u20135","simScore":null,"simPct":null},{"gameId":"22501135","gameDate":"2026-04-05","seq":2,"value":3.0,"minutes":38.6,"opp":"MIL","isHome":0,"location":"Away","simBin":"5+","simScore":null,"simPct":null}],"similarGames":[{"gameId":"22501125","gameDate":"2026-04-03","seq":1,"value":1.0,"minutes":22.283333333333335,"opp":"TOR","isHome":1,"location":"Home","simBin":"3\u20135","simScore":null,"simPct":null},{"gameId":"22501135","gameDate":"2026-04-05","seq":2,"value":3.0,"minutes":38.6,"opp":"MIL","isHome":0,"location":"Away","simBin":"5+","simScore":null,"simPct":null}],"team":"","opp":"","location":"Away","matchup":""}